pdns_zone_csv/.gitignore
pdns_zone_csv/__init__.py
pdns_zone_csv/test.py
pdns_zone_csv/zone.py
pdns_zone_csv-0.1.0.dist-info/METADATA
pdns_zone_csv-0.1.0.dist-info/WHEEL
pdns_zone_csv-0.1.0.dist-info/RECORD
