Metadata-Version: 2.4
Name: pdns-zone-csv
Version: 0.1.0
Summary: Convert a PowerDNS Authoritative Server Zone (from JSON) to CSV
Keywords: csv,dns,pdns,powerdns,zone
Requires-Python: >=3.9
